MANIFEST.in
bootstrap.py
buildout.cfg
setup.cfg
setup.py
src/AUTHORS.txt
src/HISTORY.txt
src/LICENSE.txt
src/README.txt
src/docs/conf.py
src/sphinxjp/__init__.py
src/sphinxjp.themecore.egg-info/PKG-INFO
src/sphinxjp.themecore.egg-info/SOURCES.txt
src/sphinxjp.themecore.egg-info/dependency_links.txt
src/sphinxjp.themecore.egg-info/namespace_packages.txt
src/sphinxjp.themecore.egg-info/not-zip-safe
src/sphinxjp.themecore.egg-info/requires.txt
src/sphinxjp.themecore.egg-info/top_level.txt
src/sphinxjp/themecore/__init__.py