Metadata-Version: 1.0
Name: sphinxjp.themecore
Version: 0.2.0
Summary: A sphinx theme plugin support extension. #sphinxjp
Home-page: http://bitbucket.org/shimizukawa/sphinxjp.themecore
Author: Takayuki SHIMIZUKAWA
Author-email: shimizukawa at gmail dot com
License: MIT
Keywords: sphinx,theme
Platform: UNKNOWN
Classifier: Development Status :: 4 - Beta
Classifier: License :: OSI Approved :: MIT License
Classifier: Programming Language :: Python
Classifier: Topic :: Software Development
Classifier: Topic :: Software Development :: Documentation
Classifier: Topic :: Text Processing :: Markup
